op_text/__init__.py
op_text/models.py
op_text/processing.py
op_text/utils.py
op_text-0.2.0.dist-info/LICENSE
op_text-0.2.0.dist-info/METADATA
op_text-0.2.0.dist-info/WHEEL
op_text-0.2.0.dist-info/top_level.txt
op_text-0.2.0.dist-info/RECORD
