Metadata-Version: 2.1
Name: op-text
Version: 0.2.0
Summary: Thin wrapper around HuggingFace Transformers sequence classification models for ease of use
Home-page: https://github.com/knuddj1/op_text
Author: Dean Knudson
Author-email: knuddj1@student.op.ac.nz
License: MIT
Keywords: NLP deep learning transformer pytorch BERT GPT GPT-2 google openai CMU sentiment text
Platform: UNKNOWN
Classifier: Intended Audience :: Developers
Classifier: License :: OSI Approved :: MIT License
Classifier: Programming Language :: Python :: 3
Classifier: Topic :: Scientific/Engineering :: Artificial Intelligence
Requires-Python: >=3.6
Requires-Dist: numpy
Requires-Dist: torch (>=1.0.0)
Requires-Dist: boto3
Requires-Dist: requests
Requires-Dist: tqdm
Requires-Dist: regex
Requires-Dist: sentencepiece
Requires-Dist: pytorch-transformers
